babla_translate/__init__.py
babla_translate/babla.py
babla_translate-1.0.dist-info/LICENSE
babla_translate-1.0.dist-info/METADATA
babla_translate-1.0.dist-info/WHEEL
babla_translate-1.0.dist-info/top_level.txt
babla_translate-1.0.dist-info/RECORD
