Metadata-Version: 2.1
Name: babla-translate
Version: 1.0
Summary: A module for translating words and generating examples using Bab.la dictionary.
Home-page: https://github.com/mepavv/babla_translate
Author: Michał Pawłowski
Author-email: <michal.paw000@gmail.com>
License: MIT
Keywords: translation,scraper,api
Classifier: License :: OSI Approved :: MIT License
License-File: LICENSE
Requires-Dist: requests
Requires-Dist: beautifulsoup4
